{
	"[MVP++]": [
		{
			"text": "[MVP",
			"color": [ 255, 255, 0 ],
			"pos": [ 7, 5 ]
		},
		{
			"text": "++",
			"color": [ 255, 77, 77 ],
			"pos": [ 46, 3 ]
		},
		{
			"text": "]",
			"color": [ 255, 255, 0 ],
			"pos": [ 65, 5 ]
		}
	],
	"[MVP+]": [
		{
			"text": "[MVP",
			"color": [ 0, 255, 255 ],
			"pos": [ 7, 5 ]
		},
		{
			"text": "+",
			"color": [ 255, 77, 77 ],
			"pos": [ 46, 3 ]
		},
		{
			"text": "]",
			"color": [ 0, 255, 255 ],
			"pos": [ 55, 5 ]
		}
	],
	"[MVP]": [
		{
			"text": "[MVP]",
			"color": [ 0, 255, 255 ],
			"pos": [ 7, 5 ]
		}
	],
	"[VIP+]": [
		{
			"text": "[VIP",
			"color": [ 120, 187, 255 ],
			"pos": [ 7, 5 ]
		},
		{
			"text": "+",
			"color": [ 255, 255, 255 ],
			"pos": [ 46, 3 ]
		},
		{
			"text": "]",
			"color": [ 120, 187, 255 ],
			"pos": [ 65, 5 ]
		}
	],
	"[VIP]": [
		{
			"text": "[VIP]",
			"color": [ 120, 187, 255 ],
			"pos": [ 7, 5 ]
		}
	]
}
